extractor_phone_email
